{"version":3,"kind":"Article","sha256":"b513ebd2c102200151863978e036391d608974b5f357b14f2b64e6921409bb19","slug":"index","location":"/README.md","dependencies":[],"frontmatter":{"title":"MetPy Cookbook","content_includes_title":false,"authors":[{"nameParsed":{"literal":"MetPy Maintainers","given":"MetPy","family":"Maintainers"},"name":"MetPy Maintainers","id":"contributors-myst-generated-uid-0"}],"open_access":true,"license":{"content":{"id":"CC-BY-4.0","url":"https://creativecommons.org/licenses/by/4.0/","name":"Creative Commons Attribution 4.0 International","free":true,"CC":true},"code":{"id":"Apache-2.0","url":"https://opensource.org/licenses/Apache-2.0","name":"Apache License 2.0","free":true,"osi":true}},"github":"https://github.com/projectpythia/metpy-cookbook","copyright":"2025","affiliations":[{"id":"UAlbany","name":"University at Albany (SUNY)","department":"Atmospheric and Environmental Sciences","url":"https://www.albany.edu/daes"},{"id":"CISL","name":"NSF National Center for Atmospheric Research","department":"Computational and Information Systems Lab","url":"https://www.cisl.ucar.edu"},{"id":"Unidata","name":"NSF Unidata","url":"https://www.unidata.ucar.edu"},{"id":"Argonne","name":"Argonne National Laboratory","department":"Environmental Science Division","url":"https://www.anl.gov/evs"},{"id":"CarbonPlan","name":"CarbonPlan","url":"https://carbonplan.org"},{"id":"NVIDIA","name":"NVIDIA Corporation","url":"https://www.nvidia.com/"}],"settings":{"output_matplotlib_strings":"remove"},"source_url":"https://github.com/projectpythia/metpy-cookbook/blob/main/README.md","edit_url":"https://github.com/projectpythia/metpy-cookbook/edit/main/README.md","thumbnail":"/metpy-cookbook/build/NSF-Unidata_lockup_h-08c6305cd5a753176d22cc7d81cccfa0.png","exports":[{"format":"md","filename":"README.md","url":"/metpy-cookbook/build/README-fe0f0bee5f31aa05d7e222bdb6649369.md"}]},"mdast":{"type":"root","children":[{"type":"block","children":[{"type":"div","class":"row","children":[{"type":"div","class":"column","children":[{"type":"image","url":"/metpy-cookbook/build/NSF-Unidata_lockup_h-08c6305cd5a753176d22cc7d81cccfa0.png","alt":"NSF-Unidata Logo","width":"35%","key":"fEXhnxzeuS","urlSource":"_static/NSF-Unidata_lockup_horizontal_2023_light.png"}],"key":"oZxP3svZKO"},{"type":"div","class":"column","children":[{"type":"image","url":"/metpy-cookbook/build/metpy_150x150-0e524f9e64f1889792fb49d73d3d37f5.png","alt":"MetPy Logo","width":"35%","key":"kDjChsX9QS","urlSource":"_static/metpy_150x150.png"}],"key":"TteEapgWGk"}],"key":"lx4BQZ7SBf"},{"type":"paragraph","position":{"start":{"line":12,"column":1},"end":{"line":14,"column":1}},"children":[{"type":"link","url":"https://github.com/ProjectPythia/metpy-cookbook/actions/workflows/nightly-build.yaml","position":{"start":{"line":12,"column":1},"end":{"line":12,"column":1}},"children":[{"type":"image","url":"/metpy-cookbook/build/981df9f76f4cbb88447ab61b9e9d36cb.svg","alt":"nightly-build","position":{"start":{"line":12,"column":1},"end":{"line":12,"column":1}},"key":"tzyglkyIdv","urlSource":"https://github.com/ProjectPythia/metpy-cookbook/actions/workflows/nightly-build.yaml/badge.svg"}],"urlSource":"https://github.com/ProjectPythia/metpy-cookbook/actions/workflows/nightly-build.yaml","error":true,"key":"pNIi6Tz9Ss"},{"type":"text","value":"\n","position":{"start":{"line":12,"column":1},"end":{"line":12,"column":1}},"key":"Qf54WJIQLn"},{"type":"link","url":"http://binder.projectpythia.org/v2/gh/ProjectPythia/metpy-cookbook/main?labpath=notebooks","position":{"start":{"line":12,"column":1},"end":{"line":12,"column":1}},"children":[{"type":"image","url":"/metpy-cookbook/build/59e9675f752746172a97cec992b8755b.svg","alt":"Binder","position":{"start":{"line":12,"column":1},"end":{"line":12,"column":1}},"key":"kzcOcagJl3","urlSource":"http://binder.projectpythia.org/badge_logo.svg"}],"urlSource":"http://binder.projectpythia.org/v2/gh/ProjectPythia/metpy-cookbook/main?labpath=notebooks","key":"JVinhp0Jso"},{"type":"text","value":"\n","position":{"start":{"line":12,"column":1},"end":{"line":12,"column":1}},"key":"rGSkMDJn3p"},{"type":"link","url":"https://doi.org/10.5281/zenodo.620944317","position":{"start":{"line":12,"column":1},"end":{"line":12,"column":1}},"children":[{"type":"image","url":"/metpy-cookbook/build/f94e12e2ff5e304ad3c9af9ea25d1250.svg","alt":"DOI","position":{"start":{"line":12,"column":1},"end":{"line":12,"column":1}},"key":"iLIWBovgsH","urlSource":"https://zenodo.org/badge/620944317.svg"}],"urlSource":"https://zenodo.org/badge/latestdoi/620944317","data":{"doi":"10.5281/zenodo.620944317"},"internal":false,"protocol":"doi","key":"gDHP21OPWn"}],"key":"yg8j72IkhY"},{"type":"paragraph","position":{"start":{"line":16,"column":1},"end":{"line":19,"column":1}},"children":[{"type":"text","value":"This Cookbook is the oversized recipe book for all your MetPy needs.\nWe provide a gallery of real workflows centered around meteorological data,\nand the building blocks you need to recreate those workflows or cook up brand new ones yourself.\nCreate the maps and analyses you’ve seen from class and professional institutions alike!","position":{"start":{"line":16,"column":1},"end":{"line":16,"column":1}},"key":"cvNtd5CCOI"}],"key":"Ci4TJfesCP"},{"type":"heading","depth":2,"position":{"start":{"line":21,"column":1},"end":{"line":21,"column":1}},"children":[{"type":"text","value":"Authors","position":{"start":{"line":21,"column":1},"end":{"line":21,"column":1}},"key":"HAHVucgdyY"}],"identifier":"authors","label":"Authors","html_id":"authors","implicit":true,"key":"DggCfgpB4M"},{"type":"paragraph","position":{"start":{"line":23,"column":1},"end":{"line":23,"column":1}},"children":[{"type":"text","value":"MetPy Maintainers and the MetPy Community.","position":{"start":{"line":23,"column":1},"end":{"line":23,"column":1}},"key":"Uqer9fzxjm"}],"key":"DseJ0tYvhu"},{"type":"heading","depth":3,"position":{"start":{"line":25,"column":1},"end":{"line":25,"column":1}},"children":[{"type":"text","value":"Contributors","position":{"start":{"line":25,"column":1},"end":{"line":25,"column":1}},"key":"NgOHin31uY"}],"identifier":"contributors","label":"Contributors","html_id":"contributors","implicit":true,"key":"qSZUZbDYWB"},{"type":"link","url":"https://github.com/ProjectPythia/metpy-cookbook/graphs/contributors","children":[{"type":"image","url":"/metpy-cookbook/build/7879eb4415466b18949b717be3df4263.svg","key":"iXQh8xUnum","urlSource":"https://contrib.rocks/image?repo=ProjectPythia/metpy-cookbook"}],"urlSource":"https://github.com/ProjectPythia/metpy-cookbook/graphs/contributors","error":true,"key":"hep3qX1GrU"},{"type":"heading","depth":2,"position":{"start":{"line":31,"column":1},"end":{"line":31,"column":1}},"children":[{"type":"text","value":"Structure","position":{"start":{"line":31,"column":1},"end":{"line":31,"column":1}},"key":"XUzLFcVHBm"}],"identifier":"structure","label":"Structure","html_id":"structure","implicit":true,"key":"rcrmrdem7H"},{"type":"heading","depth":3,"position":{"start":{"line":33,"column":1},"end":{"line":33,"column":1}},"children":[{"type":"text","value":"The MetPy Example Gallery","position":{"start":{"line":33,"column":1},"end":{"line":33,"column":1}},"key":"firiF3fOjS"}],"identifier":"the-metpy-example-gallery","label":"The MetPy Example Gallery","html_id":"the-metpy-example-gallery","implicit":true,"key":"DHcM856ihh"},{"type":"heading","depth":2,"position":{"start":{"line":35,"column":1},"end":{"line":35,"column":1}},"children":[{"type":"text","value":"Running the Notebooks","position":{"start":{"line":35,"column":1},"end":{"line":35,"column":1}},"key":"Rot3yBaidG"}],"identifier":"running-the-notebooks","label":"Running the Notebooks","html_id":"running-the-notebooks","implicit":true,"key":"i9IeF6uxQB"},{"type":"paragraph","position":{"start":{"line":37,"column":1},"end":{"line":37,"column":1}},"children":[{"type":"text","value":"You can either run the notebook using ","position":{"start":{"line":37,"column":1},"end":{"line":37,"column":1}},"key":"Lw9S9tF22I"},{"type":"link","url":"https://mybinder.org/","position":{"start":{"line":37,"column":1},"end":{"line":37,"column":1}},"children":[{"type":"text","value":"Binder","position":{"start":{"line":37,"column":1},"end":{"line":37,"column":1}},"key":"waFyTVreis"}],"urlSource":"https://mybinder.org/","key":"pfS2RSw3i1"},{"type":"text","value":" or on your local machine.","position":{"start":{"line":37,"column":1},"end":{"line":37,"column":1}},"key":"Yn6ZeUzTCN"}],"key":"HWq4aR2y04"},{"type":"heading","depth":3,"position":{"start":{"line":39,"column":1},"end":{"line":39,"column":1}},"children":[{"type":"text","value":"Running on Binder","position":{"start":{"line":39,"column":1},"end":{"line":39,"column":1}},"key":"YNyMYS62hi"}],"identifier":"running-on-binder","label":"Running on Binder","html_id":"running-on-binder","implicit":true,"key":"dpF6YOYiXf"},{"type":"paragraph","position":{"start":{"line":41,"column":1},"end":{"line":54,"column":1}},"children":[{"type":"text","value":"The simplest way to interact with a Jupyter Notebook is through\n","position":{"start":{"line":41,"column":1},"end":{"line":41,"column":1}},"key":"WaBvp421qS"},{"type":"link","url":"https://mybinder.org/","position":{"start":{"line":41,"column":1},"end":{"line":41,"column":1}},"children":[{"type":"text","value":"Binder","position":{"start":{"line":41,"column":1},"end":{"line":41,"column":1}},"key":"M00s7FPcdh"}],"urlSource":"https://mybinder.org/","key":"bVBNPoWkLk"},{"type":"text","value":", which enables the execution of a\n","position":{"start":{"line":41,"column":1},"end":{"line":41,"column":1}},"key":"fK1FvMJEQz"},{"type":"link","url":"https://jupyterbook.org","position":{"start":{"line":41,"column":1},"end":{"line":41,"column":1}},"children":[{"type":"text","value":"Jupyter Book","position":{"start":{"line":41,"column":1},"end":{"line":41,"column":1}},"key":"nGU8Tq9DIE"}],"urlSource":"https://jupyterbook.org","key":"NC7ikvBzuC"},{"type":"text","value":" in the cloud. The details of how this works are not\nimportant for now. All you need to know is how to launch a Pythia\nCookbooks chapter via Binder. Simply navigate your mouse to\nthe top right corner of the book chapter you are viewing and click\non the rocket ship icon, (see figure below), and be sure to select\n“launch Binder”. After a moment you should be presented with a\nnotebook that you can interact with. I.e. you’ll be able to execute\nand even change the example programs. You’ll see that the code cells\nhave no output at first, until you execute them by pressing\n","position":{"start":{"line":41,"column":1},"end":{"line":41,"column":1}},"key":"kYXyZyfwle"},{"type":"keyboard","children":[{"type":"text","value":"Shift","key":"EMhRK12gbm"}],"key":"tG5gTN4e8M"},{"type":"text","value":"+","position":{"start":{"line":41,"column":1},"end":{"line":41,"column":1}},"key":"isYQtiLVAl"},{"type":"keyboard","children":[{"type":"text","value":"Enter","key":"jSQ2kTYhcZ"}],"key":"k9plJkn0wg"},{"type":"text","value":". Complete details on how to interact with\na live Jupyter notebook are described in ","position":{"start":{"line":41,"column":1},"end":{"line":41,"column":1}},"key":"YWjEP2ZIgg"},{"type":"link","url":"https://foundations.projectpythia.org/foundations/getting-started-jupyter","position":{"start":{"line":41,"column":1},"end":{"line":41,"column":1}},"children":[{"type":"text","value":"Getting Started with\nJupyter","position":{"start":{"line":41,"column":1},"end":{"line":41,"column":1}},"key":"uwBSXLuYq3"}],"urlSource":"https://foundations.projectpythia.org/foundations/getting-started-jupyter","key":"rsvsF3SSWP"},{"type":"text","value":".","position":{"start":{"line":41,"column":1},"end":{"line":41,"column":1}},"key":"AYr3WfaG1E"}],"key":"C2qvZtKP8H"},{"type":"heading","depth":3,"position":{"start":{"line":56,"column":1},"end":{"line":56,"column":1}},"children":[{"type":"text","value":"Running on Your Own Machine","position":{"start":{"line":56,"column":1},"end":{"line":56,"column":1}},"key":"kNrBINWufW"}],"identifier":"running-on-your-own-machine","label":"Running on Your Own Machine","html_id":"running-on-your-own-machine","implicit":true,"key":"ql8XNWvjEg"},{"type":"paragraph","position":{"start":{"line":58,"column":1},"end":{"line":58,"column":1}},"children":[{"type":"text","value":"If you are interested in running this material locally on your computer, you will need to follow this workflow:","position":{"start":{"line":58,"column":1},"end":{"line":58,"column":1}},"key":"cTODtnDOII"}],"key":"sNQEeTQICR"},{"type":"list","ordered":true,"start":1,"spread":false,"position":{"start":{"line":60,"column":1},"end":{"line":79,"column":1}},"children":[{"type":"listItem","spread":true,"position":{"start":{"line":60,"column":1},"end":{"line":65,"column":1}},"children":[{"type":"paragraph","position":{"start":{"line":60,"column":1},"end":{"line":60,"column":1}},"children":[{"type":"text","value":"Clone the ","position":{"start":{"line":60,"column":1},"end":{"line":60,"column":1}},"key":"XHl4txa2Ah"},{"type":"inlineCode","value":"https://github.com/ProjectPythia/metpy-cookbook","position":{"start":{"line":60,"column":1},"end":{"line":60,"column":1}},"key":"O6bBjOY87U"},{"type":"text","value":" repository:","position":{"start":{"line":60,"column":1},"end":{"line":60,"column":1}},"key":"Z3wowstZOc"}],"key":"JVIx5O62F8"},{"type":"code","lang":"bash","value":" git clone https://github.com/ProjectPythia/metpy-cookbook.git","position":{"start":{"line":62,"column":1},"end":{"line":64,"column":1}},"key":"TCjdtrjwM8"}],"key":"ZM4a1pxios"},{"type":"listItem","spread":true,"position":{"start":{"line":66,"column":1},"end":{"line":69,"column":1}},"children":[{"type":"paragraph","position":{"start":{"line":66,"column":1},"end":{"line":66,"column":1}},"children":[{"type":"text","value":"Move into the ","position":{"start":{"line":66,"column":1},"end":{"line":66,"column":1}},"key":"wvSw6IB97y"},{"type":"inlineCode","value":"metpy-cookbook","position":{"start":{"line":66,"column":1},"end":{"line":66,"column":1}},"key":"N9IVbr5RgV"},{"type":"text","value":" directory","position":{"start":{"line":66,"column":1},"end":{"line":66,"column":1}},"key":"Q1a2wdM7h5"}],"key":"t9YxVubB9m"},{"type":"code","lang":"bash","value":"cd metpy-cookbook","position":{"start":{"line":67,"column":1},"end":{"line":69,"column":1}},"key":"yYolqyctyr"}],"key":"kysmNyaIoJ"},{"type":"listItem","spread":true,"position":{"start":{"line":70,"column":1},"end":{"line":74,"column":1}},"children":[{"type":"paragraph","position":{"start":{"line":70,"column":1},"end":{"line":70,"column":1}},"children":[{"type":"text","value":"Create and activate your conda environment from the ","position":{"start":{"line":70,"column":1},"end":{"line":70,"column":1}},"key":"xx1jQ8D1fL"},{"type":"inlineCode","value":"environment.yml","position":{"start":{"line":70,"column":1},"end":{"line":70,"column":1}},"key":"GFyNd6wGvR"},{"type":"text","value":" file","position":{"start":{"line":70,"column":1},"end":{"line":70,"column":1}},"key":"y1OUm6cgfl"}],"key":"MlKkgAmQbC"},{"type":"code","lang":"bash","value":"conda env create -f environment.yml\nconda activate metpy-cookbook","position":{"start":{"line":71,"column":1},"end":{"line":74,"column":1}},"key":"ZD6GQbJcsO"}],"key":"OF3fcbXReJ"},{"type":"listItem","spread":true,"position":{"start":{"line":75,"column":1},"end":{"line":79,"column":1}},"children":[{"type":"paragraph","position":{"start":{"line":75,"column":1},"end":{"line":75,"column":1}},"children":[{"type":"text","value":"Move into the ","position":{"start":{"line":75,"column":1},"end":{"line":75,"column":1}},"key":"CHujysbK98"},{"type":"inlineCode","value":"notebooks","position":{"start":{"line":75,"column":1},"end":{"line":75,"column":1}},"key":"GQGAipafLq"},{"type":"text","value":" directory and start up Jupyter Lab","position":{"start":{"line":75,"column":1},"end":{"line":75,"column":1}},"key":"ATL3qlnSyz"}],"key":"rgDFgbBRQq"},{"type":"code","lang":"bash","value":"cd notebooks/\njupyter lab","position":{"start":{"line":76,"column":1},"end":{"line":79,"column":1}},"key":"PTyO1akN4o"}],"key":"pgB2bseLn8"}],"key":"SpkXG2qzWQ"}],"key":"Oz3ZOP3ida"}],"key":"y2nrYdce3c"},"references":{"cite":{"order":[],"data":{}}},"footer":{"navigation":{"next":{"title":"How to Cite This Cookbook","url":"/notebooks/how-to-cite","group":"Preamble"}}},"domain":"http://localhost:3000"}