{"version":2,"kind":"Notebook","sha256":"d986deaee31794b119acff30870bc53d3dec5ac7897bb7f22b18e357a90bcecc","slug":"notebooks.specialty.smoothing-contours","location":"/notebooks/specialty/Smoothing_Contours.ipynb","dependencies":[],"frontmatter":{"title":"Smoothing Contours","content_includes_title":false,"kernelspec":{"name":"python3","display_name":"Python 3 (ipykernel)","language":"python"},"authors":[{"nameParsed":{"literal":"MetPy Maintainers","given":"MetPy","family":"Maintainers"},"name":"MetPy Maintainers","id":"contributors-myst-generated-uid-0"}],"open_access":true,"license":{"content":{"id":"CC-BY-4.0","url":"https://creativecommons.org/licenses/by/4.0/","name":"Creative Commons Attribution 4.0 International","free":true,"CC":true},"code":{"id":"Apache-2.0","url":"https://opensource.org/licenses/Apache-2.0","name":"Apache License 2.0","free":true,"osi":true}},"github":"https://github.com/projectpythia/metpy-cookbook","copyright":"2025","affiliations":[{"id":"University at Albany (State University of New York)","name":"University at Albany (State University of New York)"},{"id":"UCAR/NCAR","name":"UCAR/NCAR"}],"settings":{"output_matplotlib_strings":"remove"},"numbering":{"title":{"offset":2}},"edit_url":"https://github.com/projectpythia/metpy-cookbook/blob/main/notebooks/specialty/Smoothing_Contours.ipynb","exports":[{"format":"ipynb","filename":"Smoothing_Contours.ipynb","url":"/metpy-cookbook/build/Smoothing_Contours-a7c8afa5f787c9da8de12bee1a7d9b5e.ipynb"}]},"widgets":{},"mdast":{"type":"root","children":[{"type":"block","kind":"notebook-content","data":{"cell_marker":"\"\"\""},"children":[{"type":"paragraph","position":{"start":{"line":4,"column":1},"end":{"line":5,"column":1}},"children":[{"type":"text","value":"Demonstrate how to smooth contour values from a higher resolution\nmodel field.","position":{"start":{"line":4,"column":1},"end":{"line":4,"column":1}},"key":"KTaXtkFsXV"}],"key":"lpYkxXRXo1"},{"type":"paragraph","position":{"start":{"line":7,"column":1},"end":{"line":7,"column":1}},"children":[{"type":"text","value":"By: Kevin Goebbert","position":{"start":{"line":7,"column":1},"end":{"line":7,"column":1}},"key":"f4UR10Rb76"}],"key":"QiwemW0Cq8"},{"type":"paragraph","position":{"start":{"line":9,"column":1},"end":{"line":9,"column":1}},"children":[{"type":"text","value":"Date: 13 April 2017","position":{"start":{"line":9,"column":1},"end":{"line":9,"column":1}},"key":"MqBrNPuqpc"}],"key":"pIWmIZYvdO"}],"key":"EEcqj1elAD"},{"type":"block","kind":"notebook-content","data":{"cell_marker":"##################################","lines_to_next_cell":0},"children":[{"type":"paragraph","position":{"start":{"line":1,"column":1},"end":{"line":1,"column":1}},"children":[{"type":"text","value":"Do the needed imports","position":{"start":{"line":1,"column":1},"end":{"line":1,"column":1}},"key":"XS5AAVQO5c"}],"key":"TmlRXvazTq"}],"key":"RtTK1kAIPS"},{"type":"block","kind":"notebook-code","children":[{"type":"code","lang":"python","executable":true,"value":"from datetime import datetime, UTC\n\nimport cartopy.crs as ccrs\nimport cartopy.feature as cfeature\nimport matplotlib.pyplot as plt\nimport metpy.calc as mpcalc\nimport numpy as np\nfrom metpy.units import units\nfrom siphon.catalog import TDSCatalog\nfrom xarray.backends import NetCDF4DataStore\nimport xarray as xr","key":"OSM6uvqTij"},{"type":"output","id":"YQB9kda74mdFtpaa3Jcur","data":[],"key":"iZpDnqG00A"}],"key":"mcKRSvx8Sz"},{"type":"block","kind":"notebook-content","data":{"cell_marker":"##################################","lines_to_next_cell":0},"children":[{"type":"paragraph","position":{"start":{"line":1,"column":1},"end":{"line":1,"column":1}},"children":[{"type":"text","value":"Set up netCDF Subset Service link","position":{"start":{"line":1,"column":1},"end":{"line":1,"column":1}},"key":"XCegAWMHzm"}],"key":"jcz5CI0XQH"}],"key":"NSyeFovoST"},{"type":"block","kind":"notebook-code","children":[{"type":"code","lang":"python","executable":true,"value":"# Specify our date/time of product desired\ndt = datetime.now(UTC)\n\n# Construct the URL for our THREDDS Data Server Catalog,\n# and access our desired dataset within via NCSS\ncat = TDSCatalog('https://thredds.ucar.edu/thredds/catalog/grib/'\n                 'NCEP/NAM/CONUS_12km/latest.xml')\nncss = cat.datasets[0].subset()\n\n# Create our NCSS query with desired specifications\nquery = ncss.query()\nquery.time(dt)\nquery.add_lonlat()\nquery.variables('Geopotential_height_isobaric',\n                'u-component_of_wind_isobaric',\n                'v-component_of_wind_isobaric')\n\n# Obtain the data we've queried for\ndata = ncss.get_data(query)\n\n# Make into an xarray Dataset object\nds = xr.open_dataset(NetCDF4DataStore(data)).metpy.parse_cf()","key":"mKUUGw6mwq"},{"type":"output","id":"vtV5JhP0euzusxWSkSxoj","data":[],"key":"bX7EytXTiS"}],"key":"xAhY5RSmk7"},{"type":"block","kind":"notebook-content","data":{"cell_marker":"##################################"},"children":[{"type":"paragraph","position":{"start":{"line":1,"column":1},"end":{"line":1,"column":1}},"children":[{"type":"text","value":"Pull apart the data","position":{"start":{"line":1,"column":1},"end":{"line":1,"column":1}},"key":"Ec2bOuoa3p"}],"key":"ndLXHlTYkZ"}],"key":"TaTYUOYGIJ"},{"type":"block","kind":"notebook-code","children":[{"type":"code","lang":"python","executable":true,"value":"# Get dimension names to pull appropriate variables\n# dtime = ds.Geopotential_height_isobaric.dims[0]\n# dlev = ds.Geopotential_height_isobaric.dims[1]\n# dlat = ds.Geopotential_height_isobaric.dims[2]\n# dlon = ds.Geopotential_height_isobaric.dims[3]\n\n# Get lat and lon data, as well as time data and metadata\nlats = ds.lat\nlons = ds.lon\n\n# Need 2D lat/lons for plotting, do so if necessary\nif lats.ndim < 2:\n    lons, lats = np.meshgrid(lons, lats)\n\n# Determine the level of 500 hPa\nlev_500 = 500 * units.hPa\n\n# Create more useable times for output\ntimes = ds.Geopotential_height_isobaric.metpy.time.squeeze()\nvtimes = times.values.astype('datetime64[ms]').astype('O')\n\n# Pull out the 500 hPa Heights\nhght_500 = ds.Geopotential_height_isobaric.metpy.sel(\n    vertical=lev_500).squeeze()\nuwnd_500 = ds['u-component_of_wind_isobaric'].metpy.sel(\n    vertical=lev_500).squeeze()\nvwnd_500 = ds['v-component_of_wind_isobaric'].metpy.sel(\n    vertical=lev_500).squeeze()\n\n# Calculate the magnitude of the wind speed in kts\nsped = mpcalc.wind_speed(uwnd_500, vwnd_500).metpy.convert_units('knots')","key":"sZHpo2rUD7"},{"type":"output","id":"MjAiqYc1OVtIpdmenJvWk","data":[],"key":"OLs51rBqlR"}],"key":"OcyUG5LkKT"},{"type":"block","kind":"notebook-content","data":{"cell_marker":"##################################","lines_to_next_cell":0},"children":[{"type":"paragraph","position":{"start":{"line":1,"column":1},"end":{"line":1,"column":1}},"children":[{"type":"text","value":"Set up the projection for LCC","position":{"start":{"line":1,"column":1},"end":{"line":1,"column":1}},"key":"lqwxk4vVMf"}],"key":"tMxsVzdQxJ"}],"key":"fJAJwbsZ1K"},{"type":"block","kind":"notebook-code","children":[{"type":"code","lang":"python","executable":true,"value":"plotcrs = ccrs.LambertConformal(central_longitude=-100.0,\n                                central_latitude=45.0)\ndatacrs = ccrs.PlateCarree(central_longitude=0.)","key":"vbKPxoALXX"},{"type":"output","id":"Qgb0-HL6_ixhAQxvF85ka","data":[],"key":"Yv3uNrUCXX"}],"key":"XBWCUtDpD3"},{"type":"block","kind":"notebook-content","data":{"cell_marker":"##################################"},"children":[{"type":"paragraph","position":{"start":{"line":1,"column":1},"end":{"line":1,"column":1}},"children":[{"type":"text","value":"Subset and smooth","position":{"start":{"line":1,"column":1},"end":{"line":1,"column":1}},"key":"ifjKdAtivu"}],"key":"HoWZtCMxxS"}],"key":"jEFKyxcTtI"},{"type":"block","kind":"notebook-code","children":[{"type":"code","lang":"python","executable":true,"value":"# Smooth the 500-hPa geopotential height field\n# Be sure to only smooth the 2D field\nZ_500 = mpcalc.smooth_gaussian(hght_500, 50)","key":"t1Xoh5R7HL"},{"type":"output","id":"vpfYuXzhpNFJPVlwLsep4","data":[],"key":"DuKQnZYZTk"}],"key":"oJq95STO0i"},{"type":"block","kind":"notebook-content","data":{"cell_marker":"##################################"},"children":[{"type":"paragraph","position":{"start":{"line":1,"column":1},"end":{"line":1,"column":1}},"children":[{"type":"text","value":"Plot the contours","position":{"start":{"line":1,"column":1},"end":{"line":1,"column":1}},"key":"sdlPa7yGhn"}],"key":"qohU8ZuWdA"}],"key":"wHC2D6s0zH"},{"type":"block","kind":"notebook-code","children":[{"type":"code","lang":"python","executable":true,"value":"# Start plot with new figure and axis\nfig = plt.figure(figsize=(17., 11.))\nax = plt.subplot(1, 1, 1, projection=plotcrs)\n\n# Add some titles to make the plot readable by someone else\nplt.title('500-hPa Geo Heights (m; black), Smoothed 500-hPa Geo. '\n          'Heights (m; red)', loc='left')\nplt.title(f'VALID: {vtimes}', loc='right')\n\n# Set GAREA and add map features\nax.set_extent([-125., -67., 22., 52.], ccrs.PlateCarree())\nax.coastlines('50m', edgecolor='black', linewidth=0.75)\nax.add_feature(cfeature.STATES, linewidth=0.5)\n\n# Set the CINT\nclev500 = np.arange(5100, 6000, 60)\n\n# Plot smoothed 500-hPa contours\ncs2 = ax.contour(lons, lats, Z_500, clev500, colors='black',\n                 linewidths=3, linestyles='solid', transform=datacrs)\nc2 = plt.clabel(cs2, fontsize=12, colors='black', inline=1, inline_spacing=8,\n                fmt='%i', rightside_up=True, use_clabeltext=True)\n\n# Contour the 500 hPa heights with labels\ncs = ax.contour(lons, lats, hght_500, clev500, colors='red',\n                linewidths=2.5, linestyles='solid', alpha=0.6,\n                transform=datacrs)\ncl = plt.clabel(cs, fontsize=12, colors='red', inline=1, inline_spacing=8,\n                fmt='%i', rightside_up=True, use_clabeltext=True)","key":"DUtOsrcR6N"},{"type":"output","id":"PuMuXqdWYa_SM2PED-wno","data":[{"output_type":"display_data","metadata":{},"data":{"text/plain":{"content":"<Figure size 1700x1100 with 1 Axes>","content_type":"text/plain"},"image/png":{"content_type":"image/png","hash":"a9e5e4d270c597cede3eaf8427a35923","path":"/metpy-cookbook/build/a9e5e4d270c597cede3eaf8427a35923.png"}}}],"key":"eNhEoqD8wl"}],"key":"pPVaeUviyu"}],"key":"pNoI2rWYpX"},"references":{"cite":{"order":[],"data":{}}},"footer":{"navigation":{"prev":{"title":"Real Data Cross-Section Example","url":"/notebooks/specialty/observational-data-cross-section","group":"The MetPy Gallery"},"next":{"title":"MetPy’s Simplified Plotting Interface","url":"/notebooks/declarative","group":"The MetPy Gallery"}}},"domain":"http://localhost:3000"}